LICENSE
di_logging/__init__.py
di_logging/py.typed
di_logging-1.2.0.dist-info/LICENSE
di_logging-1.2.0.dist-info/METADATA
di_logging-1.2.0.dist-info/WHEEL
di_logging-1.2.0.dist-info/RECORD
