Metadata-Version: 2.1
Name: di-logging
Version: 1.2.0
Summary: Standard logging library for product
Home-page: https://deeperinsights.com
License: MIT
Requires-Python: >=3.9,<4.0
Classifier: License :: OSI Approved :: MIT License
Classifier: Programming Language :: Python :: 3
Classifier: Programming Language :: Python :: 3.9
Classifier: Programming Language :: Python :: 3.10
Classifier: Programming Language :: Python :: 3.11
Classifier: Programming Language :: Python :: 3.12
Requires-Dist: loguru (>=0.7.2,<0.8.0)
Project-URL: Repository, https://github.com/skimit/di-logging
